tke_aquastat/__init__.py
tke_aquastat/aquastat.csv.gzip
tke_aquastat/plotfunctions.py
tke_aquastat/slicefunctions.py
tke_aquastat/time_series_functions.py
tke_aquastat/utils.py
tiffanyke_aquastat-1.0.7.dist-info/LICENSE.txt
tiffanyke_aquastat-1.0.7.dist-info/METADATA
tiffanyke_aquastat-1.0.7.dist-info/WHEEL
tiffanyke_aquastat-1.0.7.dist-info/top_level.txt
tiffanyke_aquastat-1.0.7.dist-info/RECORD
