Metadata-Version: 2.1
Name: tiffanyke-aquastat
Version: 1.0.7
Summary: Python package for MSIA 423 Assignment 1
Home-page: https://github.com/tiffanyke888/2021-msia423-Ke-Tiffany-assignment1
Author: Tiffany Ke
Author-email: tiffanyke2021@u.northwestern.edu
License: UNKNOWN
Platform: UNKNOWN
Requires-Python: >=3.6, <4
Requires-Dist: pandas
Requires-Dist: seaborn
Requires-Dist: numpy
Provides-Extra: dev
Requires-Dist: matplotlib ; extra == 'dev'
Provides-Extra: test
Requires-Dist: pytest ; extra == 'test'
